{"cameraMode":{"drawMode":0,"name":"Shaded","section":"Shading Mode"},"sceneLighting":true,"audioPlay":false,"sceneViewState":{"m_AlwaysRefresh":false,"showFog":true,"showSkybox":true,"showFlares":true,"showImageEffects":true,"showParticleSystems":true,"showVisualEffectGraphs":true,"m_FxEnabled":true},"in2DMode":false,"pivot":{"x":278.15191650390627,"y":-473.5155029296875,"z":482.6331481933594},"rotation":{"x":-0.07493550330400467,"y":-0.7645596265792847,"z":0.08416842669248581,"w":-0.6354593634605408},"size":1.6038315296173096,"orthographic":false}